{"stats":{"minecraft:picked_up":{"minecraft:wheat_seeds":3,"minecraft:cobblestone":32},"minecraft:custom":{"minecraft:jump":22,"minecraft:open_chest":4,"minecraft:time_since_rest":7508,"minecraft:damage_dealt":49,"minecraft:crouch_one_cm":65,"minecraft:play_one_minute":7508,"minecraft:leave_game":1,"minecraft:sprint_one_cm":2071,"minecraft:walk_on_water_one_cm":4393,"minecraft:time_since_death":7508,"minecraft:walk_one_cm":1979,"minecraft:sneak_time":553,"minecraft:walk_under_water_one_cm":559,"minecraft:mob_kills":1,"minecraft:fly_one_cm":113513},"minecraft:used":{"minecraft:lever":1,"minecraft:dirt":28,"minecraft:tnt":9}},"DataVersion":2584}